<?xml version="1.0" encoding="utf-8" ?>
<LanguageData>

  <!-- EN: psychoid brewing -->
  <PsychoidBrewing.label>TODO</PsychoidBrewing.label>
  <!-- EN: Prepare psychoid leaves into a mildly euphoria-inducing and addictive tea at the campfire or cooking stove. -->
  <PsychoidBrewing.description>TODO</PsychoidBrewing.description>
  <!-- EN:  -->
  <PsychoidBrewing.discoveredLetterTitle>TODO</PsychoidBrewing.discoveredLetterTitle>
  <!-- EN:  -->
  <PsychoidBrewing.discoveredLetterText>TODO</PsychoidBrewing.discoveredLetterText>

  <!-- EN: tree sowing -->
  <TreeSowing.label>TODO</TreeSowing.label>
  <!-- EN: Sow the local biome's natural trees in your fields. -->
  <TreeSowing.description>TODO</TreeSowing.description>
  <!-- EN:  -->
  <TreeSowing.discoveredLetterTitle>TODO</TreeSowing.discoveredLetterTitle>
  <!-- EN:  -->
  <TreeSowing.discoveredLetterText>TODO</TreeSowing.discoveredLetterText>

  <!-- EN: beer brewing -->
  <Brewing.label>TODO</Brewing.label>
  <!-- EN: Build a brewery and fermenting vats to transform hops into tasty, tasty beer. -->
  <Brewing.description>TODO</Brewing.description>
  <!-- EN:  -->
  <Brewing.discoveredLetterTitle>TODO</Brewing.discoveredLetterTitle>
  <!-- EN:  -->
  <Brewing.discoveredLetterText>TODO</Brewing.discoveredLetterText>

  <!-- EN: complex furniture -->
  <ComplexFurniture.label>TODO</ComplexFurniture.label>
  <!-- EN: Build complex furniture like beds, end tables, dining chairs, armchairs, dressers, tool cabinets, billiard tables, and poker tables, vents, sarcophagi, and more. -->
  <ComplexFurniture.description>TODO</ComplexFurniture.description>
  <!-- EN:  -->
  <ComplexFurniture.discoveredLetterTitle>TODO</ComplexFurniture.discoveredLetterTitle>
  <!-- EN:  -->
  <ComplexFurniture.discoveredLetterText>TODO</ComplexFurniture.discoveredLetterText>

  <!-- EN: passive cooler -->
  <PassiveCooler.label>TODO</PassiveCooler.label>
  <!-- EN: Make passive coolers, to cool indoor spaces without using electricity. -->
  <PassiveCooler.description>TODO</PassiveCooler.description>
  <!-- EN:  -->
  <PassiveCooler.discoveredLetterTitle>TODO</PassiveCooler.discoveredLetterTitle>
  <!-- EN:  -->
  <PassiveCooler.discoveredLetterText>TODO</PassiveCooler.discoveredLetterText>

  <!-- EN: stonecutting -->
  <Stonecutting.label>TODO</Stonecutting.label>
  <!-- EN: Cut rock chunks into stone blocks for use in construction. Build beautiful stone tile floors or ugly concrete walkways. -->
  <Stonecutting.description>TODO</Stonecutting.description>
  <!-- EN:  -->
  <Stonecutting.discoveredLetterTitle>TODO</Stonecutting.discoveredLetterTitle>
  <!-- EN:  -->
  <Stonecutting.discoveredLetterText>TODO</Stonecutting.discoveredLetterText>

  <!-- EN: complex clothing -->
  <ComplexClothing.label>TODO</ComplexClothing.label>
  <!-- EN: Tailor complicated garments like pants, dusters, and cowboy hats. -->
  <ComplexClothing.description>TODO</ComplexClothing.description>
  <!-- EN:  -->
  <ComplexClothing.discoveredLetterTitle>TODO</ComplexClothing.discoveredLetterTitle>
  <!-- EN:  -->
  <ComplexClothing.discoveredLetterText>TODO</ComplexClothing.discoveredLetterText>

  <!-- EN: drug production -->
  <DrugProduction.label>TODO</DrugProduction.label>
  <!-- EN: Build a drug lab for basic drug synthesis. Further research is required to make specific drugs. -->
  <DrugProduction.description>TODO</DrugProduction.description>
  <!-- EN:  -->
  <DrugProduction.discoveredLetterTitle>TODO</DrugProduction.discoveredLetterTitle>
  <!-- EN:  -->
  <DrugProduction.discoveredLetterText>TODO</DrugProduction.discoveredLetterText>

  <!-- EN: cocoa -->
  <Cocoa.label>TODO</Cocoa.label>
  <!-- EN: Sow cocoa trees to create your own delicious chocolate. Eating chocolate fulfills the need for recreation, and it's valuable on the market too. -->
  <Cocoa.description>TODO</Cocoa.description>
  <!-- EN:  -->
  <Cocoa.discoveredLetterTitle>TODO</Cocoa.discoveredLetterTitle>
  <!-- EN:  -->
  <Cocoa.discoveredLetterText>TODO</Cocoa.discoveredLetterText>

  <!-- EN: devilstrand -->
  <Devilstrand.label>TODO</Devilstrand.label>
  <!-- EN: Plant devilstrand, a slow-growing mushroom that yields an exceptionally tough, heat-resistant plant fiber. -->
  <Devilstrand.description>TODO</Devilstrand.description>
  <!-- EN:  -->
  <Devilstrand.discoveredLetterTitle>TODO</Devilstrand.discoveredLetterTitle>
  <!-- EN:  -->
  <Devilstrand.discoveredLetterText>TODO</Devilstrand.discoveredLetterText>

  <!-- EN: carpet making -->
  <CarpetMaking.label>TODO</CarpetMaking.label>
  <!-- EN: Weave beautiful carpets from cloth. -->
  <CarpetMaking.description>TODO</CarpetMaking.description>
  <!-- EN:  -->
  <CarpetMaking.discoveredLetterTitle>TODO</CarpetMaking.discoveredLetterTitle>
  <!-- EN:  -->
  <CarpetMaking.discoveredLetterText>TODO</CarpetMaking.discoveredLetterText>

  <!-- EN: pemmican -->
  <Pemmican.label>TODO</Pemmican.label>
  <!-- EN: Make pemmican, a preserved mixture of meat and plant matter that doesn't go bad for a long time. Great for traveling. -->
  <Pemmican.description>TODO</Pemmican.description>
  <!-- EN:  -->
  <Pemmican.discoveredLetterTitle>TODO</Pemmican.discoveredLetterTitle>
  <!-- EN:  -->
  <Pemmican.discoveredLetterText>TODO</Pemmican.discoveredLetterText>

  <!-- EN: smithing -->
  <Smithing.label>TODO</Smithing.label>
  <!-- EN: Build smithies for crafting metal weapons like knives, gladii, and maces. Work metal into clean, beautiful floor tiles. -->
  <Smithing.description>TODO</Smithing.description>
  <!-- EN:  -->
  <Smithing.discoveredLetterTitle>TODO</Smithing.discoveredLetterTitle>
  <!-- EN:  -->
  <Smithing.discoveredLetterText>TODO</Smithing.discoveredLetterText>

  <!-- EN: recurve bow -->
  <RecurveBow.label>TODO</RecurveBow.label>
  <!-- EN: Build the recurve bow, an effective and inexpensive ranged weapon. -->
  <RecurveBow.description>TODO</RecurveBow.description>
  <!-- EN:  -->
  <RecurveBow.discoveredLetterTitle>TODO</RecurveBow.discoveredLetterTitle>
  <!-- EN:  -->
  <RecurveBow.discoveredLetterText>TODO</RecurveBow.discoveredLetterText>

  <!-- EN: psychite refining -->
  <PsychiteRefining.label>TODO</PsychiteRefining.label>
  <!-- EN: Refine psychoid leaves into flake and yayo, different forms of the euphoric psychite drug. -->
  <PsychiteRefining.description>TODO</PsychiteRefining.description>
  <!-- EN:  -->
  <PsychiteRefining.discoveredLetterTitle>TODO</PsychiteRefining.discoveredLetterTitle>
  <!-- EN:  -->
  <PsychiteRefining.discoveredLetterText>TODO</PsychiteRefining.discoveredLetterText>

  <!-- EN: wake-up production -->
  <WakeUpProduction.label>TODO</WakeUpProduction.label>
  <!-- EN: Synthesize wake-up, a work performance-enhancing drug which replaces the need for sleep. -->
  <WakeUpProduction.description>TODO</WakeUpProduction.description>
  <!-- EN:  -->
  <WakeUpProduction.discoveredLetterTitle>TODO</WakeUpProduction.discoveredLetterTitle>
  <!-- EN:  -->
  <WakeUpProduction.discoveredLetterText>TODO</WakeUpProduction.discoveredLetterText>

  <!-- EN: go-juice production -->
  <GoJuiceProduction.label>TODO</GoJuiceProduction.label>
  <!-- EN: Produce go-juice, a synthetic combat-performance-enhancing drug which improves shooting, melee, and movement ability, and dulls pain. -->
  <GoJuiceProduction.description>TODO</GoJuiceProduction.description>
  <!-- EN:  -->
  <GoJuiceProduction.discoveredLetterTitle>TODO</GoJuiceProduction.discoveredLetterTitle>
  <!-- EN:  -->
  <GoJuiceProduction.discoveredLetterText>TODO</GoJuiceProduction.discoveredLetterText>

  <!-- EN: penoxycyline production -->
  <PenoxycylineProduction.label>TODO</PenoxycylineProduction.label>
  <!-- EN: Produce penoxycline, a disease prevention drug which blocks plague, malaria, and more before they start. -->
  <PenoxycylineProduction.description>TODO</PenoxycylineProduction.description>
  <!-- EN:  -->
  <PenoxycylineProduction.discoveredLetterTitle>TODO</PenoxycylineProduction.discoveredLetterTitle>
  <!-- EN:  -->
  <PenoxycylineProduction.discoveredLetterText>TODO</PenoxycylineProduction.discoveredLetterText>

  <!-- EN: long blades -->
  <LongBlades.label>TODO</LongBlades.label>
  <!-- EN: Craft longswords and spears. -->
  <LongBlades.description>TODO</LongBlades.description>
  <!-- EN:  -->
  <LongBlades.discoveredLetterTitle>TODO</LongBlades.discoveredLetterTitle>
  <!-- EN:  -->
  <LongBlades.discoveredLetterText>TODO</LongBlades.discoveredLetterText>

  <!-- EN: plate armor -->
  <PlateArmor.label>TODO</PlateArmor.label>
  <!-- EN: Smith suits of plate armor from metal or wood. This heavy armor noticeably slows movement, but protects very effectively. -->
  <PlateArmor.description>TODO</PlateArmor.description>
  <!-- EN:  -->
  <PlateArmor.discoveredLetterTitle>TODO</PlateArmor.discoveredLetterTitle>
  <!-- EN:  -->
  <PlateArmor.discoveredLetterText>TODO</PlateArmor.discoveredLetterText>

  <!-- EN: greatbow -->
  <Greatbow.label>TODO</Greatbow.label>
  <!-- EN: Craft greatbows for killing enemies at great range. -->
  <Greatbow.description>TODO</Greatbow.description>
  <!-- EN:  -->
  <Greatbow.discoveredLetterTitle>TODO</Greatbow.discoveredLetterTitle>
  <!-- EN:  -->
  <Greatbow.discoveredLetterText>TODO</Greatbow.discoveredLetterText>

</LanguageData>
