<?xml version="1.0" encoding="utf-8" ?>
<LanguageData>

  <!-- EN: extremely low -->
  <ExtremelyLow.label>TODO</ExtremelyLow.label>
  <!-- EN:  -->
  <ExtremelyLow.description>TODO</ExtremelyLow.description>

  <!-- EN: very low -->
  <VeryLow.label>TODO</VeryLow.label>
  <!-- EN:  -->
  <VeryLow.description>TODO</VeryLow.description>

  <!-- EN: low -->
  <Low.label>TODO</Low.label>
  <!-- EN:  -->
  <Low.description>TODO</Low.description>

  <!-- EN: moderate -->
  <Moderate.label>TODO</Moderate.label>
  <!-- EN:  -->
  <Moderate.description>TODO</Moderate.description>

  <!-- EN: high -->
  <High.label>TODO</High.label>
  <!-- EN:  -->
  <High.description>TODO</High.description>

  <!-- EN: sky high -->
  <SkyHigh.label>TODO</SkyHigh.label>
  <!-- EN:  -->
  <SkyHigh.description>TODO</SkyHigh.description>

</LanguageData>
